speechmos/__init__.py
speechmos/aecmos.py
speechmos/dnsmos.py
speechmos/plcmos.py
speechmos/aecmos_models/Run_1663829550_Stage_0.onnx
speechmos/aecmos_models/Run_1663915512_Stage_0.onnx
speechmos/aecmos_models/Run_1668423760_Stage_0.onnx
speechmos/dnsmos_models/bak_ovr.onnx
speechmos/dnsmos_models/model_v8.onnx
speechmos/dnsmos_models/sig.onnx
speechmos/dnsmos_models/sig_bak_ovr.onnx
speechmos/pdnsmos_models/sig_bak_ovr.onnx
speechmos/plcmos_models/plcmos_v2.onnx
speechmos-0.0.1.dist-info/LICENSE.txt
speechmos-0.0.1.dist-info/METADATA
speechmos-0.0.1.dist-info/WHEEL
speechmos-0.0.1.dist-info/top_level.txt
speechmos-0.0.1.dist-info/RECORD
