Metadata-Version: 2.1
Name: speechmos
Version: 0.0.1
Summary: MOS (Mean Opinion Score) models for evaluating audio quality.
Author-email: Marju Purin <marjupurin@microsoft.com>, AEC Challenge Organizers <aec_challenge@microsoft.com>
Maintainer-email: AEC Challenge Organizers <aec_challenge@microsoft.com>, Marju Purin <marjupurin@microsoft.com>
Project-URL: AEC (acoustic echo cancellation), https://github.com/microsoft/AEC-Challenge
Project-URL: DNS (deep noise suppression), https://github.com/microsoft/DNS-Challenge
Project-URL: PLC (packet loss concealment), https://github.com/microsoft/PLC-Challenge
Keywords: aecmos,dnsmos,plcmos,acoustic echo cancellation,noise suppression,packet loss concealment,audio evaluation,speech evaluation,mean opinion score,MOS,audio quality,speech quality
Classifier: Programming Language :: Python :: 3
Classifier: License :: OSI Approved :: MIT License
Requires-Python: >=3.7
License-File: LICENSE.txt
